{"lock_version":3,"barcode":"32101113740656","indicator":"P-000011","created_by":"wrc3","last_modified_by":"pulfalight_system","create_time":"2021-02-25T14:40:13Z","system_mtime":"2021-03-10T14:49:46Z","user_mtime":"2021-03-10T14:49:46Z","type":"box","jsonmodel_type":"top_container","active_restrictions":[],"container_locations":[],"series":[],"collection":[{"ref":"/repositories/4/resources/4188","identifier":"ABID001","display_string":"AbID Testing Resource #1"}],"uri":"/repositories/4/top_containers/118100","repository":{"ref":"/repositories/4"},"restricted":false,"is_linked_to_published_record":false,"display_string":"Box P-000011: [Barcode: 32101113740656]","long_display_string":"Box P-000011 [Barcode: 32101113740656], ABID001, AbID Testing Resource #1"}
