{"child_count":28,"waypoints":1,"waypoint_size":200,"title":"General Manuscripts Collection","uri":"/repositories/4/resources/1870","slugged_url":"","jsonmodel_type":"resource","parsed_title":"General Manuscripts Collection","level":"collection","precomputed_waypoints":{"":{"0":[{"child_count":0,"waypoints":0,"waypoint_size":200,"title":"C.H. Andrews Speech \"On National Ingratitude\"","slugged_url":"","parsed_title":"C.H. Andrews Speech \"On National Ingratitude\"","uri":"/repositories/4/archival_objects/597759","position":0,"parent_id":null,"jsonmodel_type":"archival_object","level":"file","dates":[{"type":"inclusive","label":"creation","expression":"1820","begin":"1820","end":"1820"}],"containers":[{"instance_type":"mixed_materials","top_container_type":"box","top_container_indicator":"3","top_container_barcode":"32101092753035"}]}]}}}